{
    "Changes": [
        {
            "LogName": "Loading Council meeting event",
            "Action": "EditData",
            "Target": "Data/Events/ManorHouse",
            "Entries": {
                "{{ModId}}_WorriedLewisEvent/Hn {{ModId}}_TalkingToVotersMail": "continue/5 6/farmer -1000 -1000 0 lewis 7 6 3 marnie 6 6 1/skippable/pause 1000/speak lewis \"{{i18n:{{ModId}}_Events.WorriedLewis_1}}\"/speak marnie \"{{i18n:{{ModId}}_Events.WorriedLewis_2}}\"/speak lewis \"{{i18n:{{ModId}}_Events.WorriedLewis_3}}\"/warp farmer 5 11/speak marnie \"{{i18n:{{ModId}}_Events.WorriedLewis_4}}\"/move marnie -2 0 3/move marnie 0 6 3/warp marnie -1000 -1000/speak lewis \"{{i18n:{{ModId}}_Events.WorriedLewis_5}}\"/pause 1000/globalFade/viewport 1000 1000/end"
            }
        }
    ]
}