{
    "Changes": [
        {
            "LogName": "Loading {{ModId}}_ManorHouse into assets",
            "Action": "Load",
            "Target": "Maps/{{ModId}}_ManorHouse",
            "FromFile": "Assets/Maps/Interior/ManorHouse.tmx"
        },
        {
            "LogName": "Updating Data/Locations to add {{ModId}}_ManorHouse",
            "Action": "EditData",
            "Target": "Data/Locations",
            "Entries": {
                "{{ModId}}_ManorHouse": {
                    "CreateOnLoad": {
                        "MapPath": "Maps/{{ModId}}_ManorHouse"
                    },
                    "DisplayName": "Manor House",
                    "DefaultArrivalTile": {
                        "X": 7,
                        "Y": 9
                    },
                    "ExcludeFromNpcPathfinding": false,
                    "ArtifactSpots": [],
                    "FishAreas": {},
                    "Fish": [],
                    "Forage": [],
                    "MusicContext": "Default"
                }
            }
        },
        //{
        //    "LogName": "Updated Data/ChairTiles with Mayor Chair",
        //    "Action": "EditData",
        //    "Target": "Data/ChairTiles",
        //    "Entries": {
        //        "{{ModId}}_Misc_Tilesheet/18/1": "1/1/down/couch/-1/-1/false"
        //    }
        //},
        {
            "LogName": "Loading strings for CouncilMeeting",
            "Action": "EditData",
            "Target": "Strings/StringsFromMaps",
            "Entries": {
                "{{ModId}}_HoldCouncilMeeting": "{{i18n:{{ModId}}_MapStrings.HoldCouncilMeeting}}",
                "{{ModId}}_MeetingPlanned": "{{i18n:{{ModId}}_MapStrings.MeetingPlanned}}",
                "{{ModId}}_AlreadyPlanned": "{{i18n:{{ModId}}_MapStrings.AlreadyPlanned}}",
                "{{ModId}}_NoNewMeetings": "{{i18n:{{ModId}}_MapStrings.NoNewMeetings}}",
                "{{ModId}}_MeetingOption0": "{{i18n:{{ModId}}_MapStrings.MeetingOption0}}",
                "{{ModId}}_MeetingOption1": "{{i18n:{{ModId}}_MapStrings.MeetingOption1}}",
                "{{ModId}}_MeetingOption2": "{{i18n:{{ModId}}_MapStrings.MeetingOption2}}",
                "{{ModId}}_MeetingOption3": "{{i18n:{{ModId}}_MapStrings.MeetingOption3}}",
                "{{ModId}}_MeetingOption4": "{{i18n:{{ModId}}_MapStrings.MeetingOption4}}",
                "{{ModId}}_MeetingOption5": "{{i18n:{{ModId}}_MapStrings.MeetingOption5}}"
            }
        }
    ]
}